xdrlib3/__init__.py
xdrlib3/py.typed
xdrlib3-0.1.0.dist-info/METADATA
xdrlib3-0.1.0.dist-info/WHEEL
xdrlib3-0.1.0.dist-info/RECORD
