Metadata-Version: 2.1
Name: xdrlib3
Version: 0.1.0
Summary: A forked version of `xdrlib`, a module for encoding and decoding XDR (External Data Representation) data in Python.
Home-page: https://github.com/overcat/xdrlib3
Keywords: xdrlib,xdr
Author: overcat
Author-email: 4catcode@gmail.com
Maintainer: overcat
Maintainer-email: 4catcode@gmail.com
Requires-Python: >=3.7,<4.0
Classifier: Development Status :: 5 - Production/Stable
Classifier: Intended Audience :: Developers
Classifier: License :: OSI Approved :: Apache Software License
Classifier: Operating System :: OS Independent
Classifier: Programming Language :: Python
Classifier: Programming Language :: Python :: 3
Classifier: Programming Language :: Python :: 3.7
Classifier: Programming Language :: Python :: 3.8
Classifier: Programming Language :: Python :: 3.9
Classifier: Programming Language :: Python :: 3.10
Classifier: Programming Language :: Python :: 3.11
Classifier: Programming Language :: Python :: 3 :: Only
Classifier: Programming Language :: Python :: Implementation :: CPython
Classifier: Programming Language :: Python :: Implementation :: PyPy
Classifier: Topic :: Software Development :: Libraries :: Python Modules
Classifier: Typing :: Typed
Project-URL: Bug Tracker, https://github.com/overcat/xdrlib3/issues
Project-URL: Documentation, https://github.com/overcat/xdrlib3
Project-URL: Repository, https://github.com/overcat/xdrlib3
